bytedance_tf2_cambricon/__init__.py
bytedance_tf2_cambricon-0.0.1.dist-info/METADATA
bytedance_tf2_cambricon-0.0.1.dist-info/WHEEL
bytedance_tf2_cambricon-0.0.1.dist-info/top_level.txt
bytedance_tf2_cambricon-0.0.1.dist-info/RECORD
